jinja2_iso8601.py
jinja2_iso8601-1.0.0.dist-info/WHEEL
jinja2_iso8601-1.0.0.dist-info/METADATA
jinja2_iso8601-1.0.0.dist-info/RECORD
