Metadata-Version: 2.1
Name: jinja2_iso8601
Version: 1.0.0
Summary: Adds `parse_date` and `format_date` filters to Jinja.
Author-email: David Baumgold <david@davidbaumgold.com>
Requires-Dist: Jinja2 >=3.1
Requires-Dist: iso8601 >=1.0
Requires-Dist: pytest >=7.1 ; extra == "test"
Provides-Extra: test
